{
  "fallback:default": {
    "ts": 1762089426410,
    "data": [
      {
        "id": "GB1342",
        "title": "Pride and Prejudice",
        "author": "Jane Austen",
        "year": 1813,
        "subjects": [],
        "cover_url": "https://www.gutenberg.org/cache/epub/1342/pg1342.cover.medium.jpg",
        "gutenberg_id": 1342,
        "source_url": "https://www.gutenberg.org/files/1342/1342-0.txt",
        "content_preview": "*** START OF THE PROJECT GUTENBERG EBOOK 1342 ***\r\n\r\n\r\n\r\n\r\n                            [Illustration:\r\n\r\n                             GEORGE ALLEN\r\n                               PUBLISHER\r\n\r\n                        156 CHARING CROSS ROAD\r\n                                LONDON\r\n\r\n                             RUSKIN HOUSE\r\n                                   ]\r\n\r\n                            [Illustration:\r\n\r\n               _Reading Jane’s Letters._      _Chap 34._\r\n                               ...",
        "edition_info": {
          "publish_date": 1813,
          "language": "en"
        }
      },
      {
        "id": "GB84",
        "title": "Frankenstein",
        "author": "Mary Shelley",
        "year": 1818,
        "subjects": [],
        "cover_url": "https://www.gutenberg.org/cache/epub/84/pg84.cover.medium.jpg",
        "gutenberg_id": 84,
        "source_url": "https://www.gutenberg.org/files/84/84-0.txt",
        "content_preview": "*** START OF THE PROJECT GUTENBERG EBOOK 84 ***\n\nFrankenstein;\n\nor, the Modern Prometheus\n\nby Mary Wollstonecraft (Godwin) Shelley\n\n\n CONTENTS\n\n Letter 1\n Letter 2\n Letter 3\n Letter 4\n Chapter 1\n Chapter 2\n Chapter 3\n Chapter 4\n Chapter 5\n Chapter 6\n Chapter 7\n Chapter 8\n Chapter 9\n Chapter 10\n Chapter 11\n Chapter 12\n Chapter 13\n Chapter 14\n Chapter 15\n Chapter 16\n Chapter 17\n Chapter 18\n Chapter 19\n Chapter 20\n Chapter 21\n Chapter 22\n Chapter 23\n Chapter 24\n\n\n\n\nLetter 1\n\n_To Mrs. Saville, Engla...",
        "edition_info": {
          "publish_date": 1818,
          "language": "en"
        }
      },
      {
        "id": "GB11",
        "title": "Alice's Adventures in Wonderland",
        "author": "Lewis Carroll",
        "year": 1865,
        "subjects": [],
        "cover_url": "https://www.gutenberg.org/cache/epub/11/pg11.cover.medium.jpg",
        "gutenberg_id": 11,
        "source_url": "https://www.gutenberg.org/files/11/11-0.txt",
        "content_preview": "*** START OF THE PROJECT GUTENBERG EBOOK 11 ***\n\n[Illustration]\n\n\n\n\nAlice’s Adventures in Wonderland\n\nby Lewis Carroll\n\nTHE MILLENNIUM FULCRUM EDITION 3.0\n\nContents\n\n CHAPTER I.     Down the Rabbit-Hole\n CHAPTER II.    The Pool of Tears\n CHAPTER III.   A Caucus-Race and a Long Tale\n CHAPTER IV.    The Rabbit Sends in a Little Bill\n CHAPTER V.     Advice from a Caterpillar\n CHAPTER VI.    Pig and Pepper\n CHAPTER VII.   A Mad Tea-Party\n CHAPTER VIII.  The Queen’s Croquet-Ground\n CHAPTER IX.    The...",
        "edition_info": {
          "publish_date": 1865,
          "language": "en"
        }
      },
      {
        "id": "GB2701",
        "title": "Moby-Dick",
        "author": "Herman Melville",
        "year": 1851,
        "subjects": [],
        "cover_url": "https://www.gutenberg.org/cache/epub/2701/pg2701.cover.medium.jpg",
        "gutenberg_id": 2701,
        "source_url": "https://www.gutenberg.org/files/2701/2701-0.txt",
        "content_preview": "*** START OF THE PROJECT GUTENBERG EBOOK 2701 ***\r\n\r\n\r\n\r\n\r\nMOBY-DICK;\r\n\r\nor, THE WHALE.\r\n\r\nBy Herman Melville\r\n\r\n\r\n\r\nCONTENTS\r\n\r\nETYMOLOGY.\r\n\r\nEXTRACTS (Supplied by a Sub-Sub-Librarian).\r\n\r\nCHAPTER 1. Loomings.\r\n\r\nCHAPTER 2. The Carpet-Bag.\r\n\r\nCHAPTER 3. The Spouter-Inn.\r\n\r\nCHAPTER 4. The Counterpane.\r\n\r\nCHAPTER 5. Breakfast.\r\n\r\nCHAPTER 6. The Street.\r\n\r\nCHAPTER 7. The Chapel.\r\n\r\nCHAPTER 8. The Pulpit.\r\n\r\nCHAPTER 9. The Sermon.\r\n\r\nCHAPTER 10. A Bosom Friend.\r\n\r\nCHAPTER 11. Nightgown.\r\n\r\nCHAPTER ...",
        "edition_info": {
          "publish_date": 1851,
          "language": "en"
        }
      },
      {
        "id": "GB1661",
        "title": "The Adventures of Sherlock Holmes",
        "author": "Arthur Conan Doyle",
        "year": 1892,
        "subjects": [],
        "cover_url": "https://www.gutenberg.org/cache/epub/1661/pg1661.cover.medium.jpg",
        "gutenberg_id": 1661,
        "source_url": "https://www.gutenberg.org/files/1661/1661-0.txt",
        "content_preview": "The Project Gutenberg eBook of The Adventures of Sherlock Holmes,\r\nby Arthur Conan Doyle\r\n\r\nThis eBook is for the use of anyone anywhere in the United States and\r\nmost other parts of the world at no cost and with almost no restrictions\r\nwhatsoever. You may copy it, give it away or re-use it under the terms\r\nof the Project Gutenberg License included with this eBook or online at\r\nwww.gutenberg.org. If you are not located in the United States, you\r\nwill have to check the laws of the country where y...",
        "edition_info": {
          "publish_date": 1892,
          "language": "en"
        }
      },
      {
        "id": "GB2542",
        "title": "A Doll's House",
        "author": "Henrik Ibsen",
        "year": 1879,
        "subjects": [],
        "cover_url": "https://www.gutenberg.org/cache/epub/2542/pg2542.cover.medium.jpg",
        "gutenberg_id": 2542,
        "source_url": "https://www.gutenberg.org/files/2542/2542-0.txt",
        "content_preview": "﻿*** START OF THE PROJECT GUTENBERG EBOOK 2542 ***\r\n\r\n\r\n\r\n\r\nA Doll’s House\r\n\r\nby Henrik Ibsen\r\n\r\n\r\nContents\r\n\r\n ACT I.\r\n ACT II.\r\n ACT III.\r\n\r\n\r\n DRAMATIS PERSONAE\r\n\r\nTorvald Helmer.\r\nNora, his wife.\r\nDoctor Rank.\r\nMrs Linde.\r\nNils Krogstad.\r\nHelmer’s three young children.\r\nAnne, their nurse.\r\nA Housemaid.\r\nA Porter.\r\n\r\n_[The action takes place in Helmer’s house.]_\r\n\r\n\r\n\r\n\r\nA DOLL’S HOUSE\r\n\r\n\r\n\r\n\r\nACT I\r\n\r\n\r\n_[SCENE.—A room furnished comfortably and tastefully, but not\r\nextravagantly. At the bac...",
        "edition_info": {
          "publish_date": 1879,
          "language": "en"
        }
      },
      {
        "id": "GB4300",
        "title": "Ulysses",
        "author": "James Joyce",
        "year": 1922,
        "subjects": [],
        "cover_url": "https://www.gutenberg.org/cache/epub/4300/pg4300.cover.medium.jpg",
        "gutenberg_id": 4300,
        "source_url": "https://www.gutenberg.org/files/4300/4300-0.txt",
        "content_preview": "*** START OF THE PROJECT GUTENBERG EBOOK 4300 ***\r\n\r\n[Illustration]\r\n\r\n\r\n\r\n\r\nUlysses\r\n\r\n\r\nby James Joyce\r\n\r\n\r\nContents\r\n\r\n — I —\r\n\r\n [  1 ]\r\n [  2 ]\r\n [  3 ]\r\n\r\n — II —\r\n\r\n [  4 ]\r\n [  5 ]\r\n [  6 ]\r\n [  7 ]\r\n [  8 ]\r\n [  9 ]\r\n [ 10 ]\r\n [ 11 ]\r\n [ 12 ]\r\n [ 13 ]\r\n [ 14 ]\r\n [ 15 ]\r\n\r\n — III —\r\n\r\n [ 16 ]\r\n [ 17 ]\r\n [ 18 ]\r\n\r\n\r\n\r\n\r\n— I —\r\n\r\n\r\n[ 1 ]\r\n\r\nStately, plump Buck Mulligan came from the stairhead, bearing a bowl of\r\nlather on which a mirror and a razor lay crossed. A yellow\r\ndressinggown, ungi...",
        "edition_info": {
          "publish_date": 1922,
          "language": "en"
        }
      },
      {
        "id": "GB345",
        "title": "Dracula",
        "author": "Bram Stoker",
        "year": 1897,
        "subjects": [],
        "cover_url": "https://www.gutenberg.org/cache/epub/345/pg345.cover.medium.jpg",
        "gutenberg_id": 345,
        "source_url": "https://www.gutenberg.org/files/345/345-0.txt",
        "content_preview": "*** START OF THE PROJECT GUTENBERG EBOOK 345 ***\r\n\r\n\r\n\r\n\r\n                                DRACULA\r\n\r\n                                  _by_\r\n\r\n                              Bram Stoker\r\n\r\n                        [Illustration: colophon]\r\n\r\n                                NEW YORK\r\n\r\n                            GROSSET & DUNLAP\r\n\r\n                              _Publishers_\r\n\r\n      Copyright, 1897, in the United States of America, according\r\n                   to Act of Congress, by Bram Stoker\r\n...",
        "edition_info": {
          "publish_date": 1897,
          "language": "en"
        }
      },
      {
        "id": "GB98",
        "title": "A Tale of Two Cities",
        "author": "Charles Dickens",
        "year": 1859,
        "subjects": [],
        "cover_url": "https://www.gutenberg.org/cache/epub/98/pg98.cover.medium.jpg",
        "gutenberg_id": 98,
        "source_url": "https://www.gutenberg.org/files/98/98-0.txt",
        "content_preview": "The Project Gutenberg eBook of A Tale of Two Cities, by Charles Dickens\r\n\r\nThis eBook is for the use of anyone anywhere in the United States and\r\nmost other parts of the world at no cost and with almost no restrictions\r\nwhatsoever. You may copy it, give it away or re-use it under the terms\r\nof the Project Gutenberg License included with this eBook or online at\r\nwww.gutenberg.org. If you are not located in the United States, you\r\nwill have to check the laws of the country where you are located be...",
        "edition_info": {
          "publish_date": 1859,
          "language": "en"
        }
      },
      {
        "id": "GB1400",
        "title": "Great Expectations",
        "author": "Charles Dickens",
        "year": 1861,
        "subjects": [],
        "cover_url": "https://www.gutenberg.org/cache/epub/1400/pg1400.cover.medium.jpg",
        "gutenberg_id": 1400,
        "source_url": "https://www.gutenberg.org/files/1400/1400-0.txt",
        "content_preview": "*** START OF THE PROJECT GUTENBERG EBOOK 1400 ***\r\n\r\n[Illustration]\r\n\r\n\r\n\r\n\r\nGreat Expectations\r\n\r\n[1867 Edition]\r\n\r\nby Charles Dickens\r\n\r\n\r\nContents\r\n\r\n Chapter I.\r\n Chapter II.\r\n Chapter III.\r\n Chapter IV.\r\n Chapter V.\r\n Chapter VI.\r\n Chapter VII.\r\n Chapter VIII.\r\n Chapter IX.\r\n Chapter X.\r\n Chapter XI.\r\n Chapter XII.\r\n Chapter XIII.\r\n Chapter XIV.\r\n Chapter XV.\r\n Chapter XVI.\r\n Chapter XVII.\r\n Chapter XVIII.\r\n Chapter XIX.\r\n Chapter XX.\r\n Chapter XXI.\r\n Chapter XXII.\r\n Chapter XXIII.\r\n Chapte...",
        "edition_info": {
          "publish_date": 1861,
          "language": "en"
        }
      }
    ]
  }
}